MANIFEST.in
README.txt
setup.py
djlime_settings.egg-info/PKG-INFO
djlime_settings.egg-info/SOURCES.txt
djlime_settings.egg-info/dependency_links.txt
djlime_settings.egg-info/top_level.txt
settings/__init__.py
settings/admin.py
settings/models.py
settings/locale/ru/LC_MESSAGES/django.mo
settings/locale/ru/LC_MESSAGES/django.po
settings/locale/uk/LC_MESSAGES/django.mo
settings/locale/uk/LC_MESSAGES/django.po
settings/migrations/0001_initial.py
settings/migrations/__init__.py
settings/templatetags/__init__.py
settings/templatetags/settings_tags.py