Metadata-Version: 1.0
Name: djlime-settings
Version: 1.0.2
Summary: The application settings.
Home-page: https://github.com/whitespy/djlime-settings
Author: Andrey Butenko
Author-email: whitespysoftware@yandex.ru
License: UNKNOWN
Platform: any
